synthefy/__init__.py
synthefy/api_client.py
synthefy/data_models.py
synthefy-2.0.5.dist-info/METADATA
synthefy-2.0.5.dist-info/WHEEL
synthefy-2.0.5.dist-info/RECORD
