Metadata-Version: 2.4
Name: synthefy
Version: 2.0.5
Summary: Python client for the Synthefy API forecasting service
Project-URL: Homepage, https://synthefy.com
Author-email: Synthefy <contact@synthefy.com>
Maintainer-email: Synthefy <contact@synthefy.com>
License: MIT
Keywords: api,forecasting,machine-learning,time-series
Classifier: Development Status :: 4 - Beta
Classifier: Intended Audience :: Developers
Classifier: Intended Audience :: Science/Research
Classifier: License :: OSI Approved :: MIT License
Classifier: Operating System :: OS Independent
Classifier: Programming Language :: Python :: 3
Classifier: Programming Language :: Python :: 3.8
Classifier: Programming Language :: Python :: 3.9
Classifier: Programming Language :: Python :: 3.10
Classifier: Programming Language :: Python :: 3.11
Classifier: Programming Language :: Python :: 3.12
Classifier: Topic :: Scientific/Engineering :: Artificial Intelligence
Classifier: Topic :: Scientific/Engineering :: Information Analysis
Classifier: Topic :: Software Development :: Libraries :: Python Modules
Requires-Python: >=3.9
Requires-Dist: httpx<0.28.0,>=0.24.0
Requires-Dist: numpy>=1.20.0
Requires-Dist: pandas>=1.3.0
Requires-Dist: pydantic>=2.0.0
Requires-Dist: pytest-asyncio>=0.25.0
Requires-Dist: pytest==8.3.2
